firstbatch/__init__.py
firstbatch/client.py
firstbatch/maps.py
firstbatch/request_handler.py
firstbatch/utils.py
firstbatch_py-0.1.9.dist-info/LICENSE
firstbatch_py-0.1.9.dist-info/METADATA
firstbatch_py-0.1.9.dist-info/WHEEL
firstbatch_py-0.1.9.dist-info/top_level.txt
firstbatch_py-0.1.9.dist-info/RECORD
