Metadata-Version: 2.1
Name: firstbatch-py
Version: 0.1.9
Summary: FirstBatch Python Client
License: { file="LICENSE" }
License-File: LICENSE
